CONTRIBUTORS
LICENCE
MANIFEST.in
README
README.markdown
VERSION
example.py
setup.py
pyxmli/__init__.py
pyxmli/xmldsig.py
pyxmli.egg-info/PKG-INFO
pyxmli.egg-info/SOURCES.txt
pyxmli.egg-info/dependency_links.txt
pyxmli.egg-info/requires.txt
pyxmli.egg-info/top_level.txt
pyxmli.egg-info/zip-safe
tests/id_rsa
tests/id_rsa.pub