Metadata-Version: 1.0
Name: pyxmli
Version: 2.1.5
Summary: Create XMLi 2.0 compliant invoices in Python
Home-page: http://github.com/Greendizer/PyXMLi
Author: Greendizer
Author-email: developers@xmli.com
License: The MIT Licence
